{
  "version": 2,
  "themes": [
    "Identity",
    "Career & Money",
    "Love & Relationships",
    "Home & Space",
    "Beauty & Wellness",
    "Travel & Adventure",
    "Organization & Plan",
    "Aesthetic & Mood"
  ],
  "images": [
    {
      "id": "identity-01-journal-desk",
      "theme": "Identity",
      "category": "Identity",
      "url": "/boardimagelibrary/identity/01-journal-desk.png",
      "description": "Journal desk",
      "tags": [
        "identity"
      ]
    },
    {
      "id": "identity-02-vintage-compass-map",
      "theme": "Identity",
      "category": "Identity",
      "url": "/boardimagelibrary/identity/02-vintage-compass-map.png",
      "description": "Vintage compass map",
      "tags": [
        "identity"
      ]
    },
    {
      "id": "identity-03-hiking-boot-trail",
      "theme": "Identity",
      "category": "Identity",
      "url": "/boardimagelibrary/identity/03-hiking-boot-trail.png",
      "description": "Hiking boot trail",
      "tags": [
        "identity"
      ]
    },
    {
      "id": "identity-04-origami-cranes-linen",
      "theme": "Identity",
      "category": "Identity",
      "url": "/boardimagelibrary/identity/04-origami-cranes-linen.png",
      "description": "Origami cranes linen",
      "tags": [
        "identity"
      ]
    },
    {
      "id": "identity-05-graduation-cap-books",
      "theme": "Identity",
      "category": "Identity",
      "url": "/boardimagelibrary/identity/05-graduation-cap-books.png",
      "description": "Graduation cap books",
      "tags": [
        "identity"
      ]
    },
    {
      "id": "identity-06-mirror-sunlit-room",
      "theme": "Identity",
      "category": "Identity",
      "url": "/boardimagelibrary/identity/06-mirror-sunlit-room.png",
      "description": "Mirror sunlit room",
      "tags": [
        "identity"
      ]
    },
    {
      "id": "identity-07-phoenix-feather-quill-inkwell",
      "theme": "Identity",
      "category": "Identity",
      "url": "/boardimagelibrary/identity/07-phoenix-feather-quill-inkwell.png",
      "description": "Phoenix feather quill inkwell",
      "tags": [
        "identity"
      ]
    },
    {
      "id": "identity-08-compass-map-keys",
      "theme": "Identity",
      "category": "Identity",
      "url": "/boardimagelibrary/identity/08-compass-map-keys.png",
      "description": "Compass map keys",
      "tags": [
        "identity"
      ]
    },
    {
      "id": "identity-09-open-door-sunlight",
      "theme": "Identity",
      "category": "Identity",
      "url": "/boardimagelibrary/identity/09-open-door-sunlight.png",
      "description": "Open door sunlight",
      "tags": [
        "identity"
      ]
    },
    {
      "id": "identity-10-butterfly-garden",
      "theme": "Identity",
      "category": "Identity",
      "url": "/boardimagelibrary/identity/10-butterfly-garden.png",
      "description": "Butterfly garden",
      "tags": [
        "identity"
      ]
    },
    {
      "id": "identity-11-artist-palette-brushes",
      "theme": "Identity",
      "category": "Identity",
      "url": "/boardimagelibrary/identity/11-artist-palette-brushes.png",
      "description": "Artist palette brushes",
      "tags": [
        "identity"
      ]
    },
    {
      "id": "identity-12-mountain-summit-sunrise",
      "theme": "Identity",
      "category": "Identity",
      "url": "/boardimagelibrary/identity/12-mountain-summit-sunrise.png",
      "description": "Mountain summit sunrise",
      "tags": [
        "identity"
      ]
    },
    {
      "id": "identity-13-seedling-soil-pot",
      "theme": "Identity",
      "category": "Identity",
      "url": "/boardimagelibrary/identity/13-seedling-soil-pot.png",
      "description": "Seedling soil pot",
      "tags": [
        "identity"
      ]
    },
    {
      "id": "identity-14-lighthouse-coast",
      "theme": "Identity",
      "category": "Identity",
      "url": "/boardimagelibrary/identity/14-lighthouse-coast.png",
      "description": "Lighthouse coast",
      "tags": [
        "identity"
      ]
    },
    {
      "id": "identity-15-chess-board-strategy",
      "theme": "Identity",
      "category": "Identity",
      "url": "/boardimagelibrary/identity/15-chess-board-strategy.png",
      "description": "Chess board strategy",
      "tags": [
        "identity"
      ]
    },
    {
      "id": "identity-16-fingerprint-clay",
      "theme": "Identity",
      "category": "Identity",
      "url": "/boardimagelibrary/identity/16-fingerprint-clay.png",
      "description": "Fingerprint clay",
      "tags": [
        "identity"
      ]
    },
    {
      "id": "identity-17-name-badge-cork-board",
      "theme": "Identity",
      "category": "Identity",
      "url": "/boardimagelibrary/identity/17-name-badge-cork-board.png",
      "description": "Name badge cork board",
      "tags": [
        "identity"
      ]
    },
    {
      "id": "identity-18-constellation-night-sky",
      "theme": "Identity",
      "category": "Identity",
      "url": "/boardimagelibrary/identity/18-constellation-night-sky.png",
      "description": "Constellation night sky",
      "tags": [
        "identity"
      ]
    },
    {
      "id": "identity-19-path-splitting-forest",
      "theme": "Identity",
      "category": "Identity",
      "url": "/boardimagelibrary/identity/19-path-splitting-forest.png",
      "description": "Path splitting forest",
      "tags": [
        "identity"
      ]
    },
    {
      "id": "identity-20-chameleon-leaf",
      "theme": "Identity",
      "category": "Identity",
      "url": "/boardimagelibrary/identity/20-chameleon-leaf.png",
      "description": "Chameleon leaf",
      "tags": [
        "identity"
      ]
    },
    {
      "id": "career-money-01-modern-minimalist-desk-closed-laptop-notebook",
      "theme": "Career & Money",
      "category": "Career & Money",
      "url": "/boardimagelibrary/career-money/01-modern-minimalist-desk-closed-laptop-notebook.png",
      "description": "Modern minimalist desk closed laptop notebook",
      "tags": [
        "career-money"
      ]
    },
    {
      "id": "career-money-02-stack-gold-coins-dark-slate",
      "theme": "Career & Money",
      "category": "Career & Money",
      "url": "/boardimagelibrary/career-money/02-stack-gold-coins-dark-slate.png",
      "description": "Stack gold coins dark slate",
      "tags": [
        "career-money"
      ]
    },
    {
      "id": "career-money-03-leather-briefcase-bench-glass-office-lobby",
      "theme": "Career & Money",
      "category": "Career & Money",
      "url": "/boardimagelibrary/career-money/03-leather-briefcase-bench-glass-office-lobby.png",
      "description": "Leather briefcase bench glass office lobby",
      "tags": [
        "career-money"
      ]
    },
    {
      "id": "career-money-04-glass-skyscraper-facade-reflecting-sky",
      "theme": "Career & Money",
      "category": "Career & Money",
      "url": "/boardimagelibrary/career-money/04-glass-skyscraper-facade-reflecting-sky.png",
      "description": "Glass skyscraper facade reflecting sky",
      "tags": [
        "career-money"
      ]
    },
    {
      "id": "career-money-05-piggy-bank-ceramic-shelf",
      "theme": "Career & Money",
      "category": "Career & Money",
      "url": "/boardimagelibrary/career-money/05-piggy-bank-ceramic-shelf.png",
      "description": "Piggy bank ceramic shelf",
      "tags": [
        "career-money"
      ]
    },
    {
      "id": "career-money-06-calculator-coffee-cup-receipts-flat-lay",
      "theme": "Career & Money",
      "category": "Career & Money",
      "url": "/boardimagelibrary/career-money/06-calculator-coffee-cup-receipts-flat-lay.png",
      "description": "Calculator coffee cup receipts flat lay",
      "tags": [
        "career-money"
      ]
    },
    {
      "id": "career-money-07-blueprint-rolls-hard-hat-table",
      "theme": "Career & Money",
      "category": "Career & Money",
      "url": "/boardimagelibrary/career-money/07-blueprint-rolls-hard-hat-table.png",
      "description": "Blueprint rolls hard hat table",
      "tags": [
        "career-money"
      ]
    },
    {
      "id": "career-money-08-trophy-mahogany-desk",
      "theme": "Career & Money",
      "category": "Career & Money",
      "url": "/boardimagelibrary/career-money/08-trophy-mahogany-desk.png",
      "description": "Trophy mahogany desk",
      "tags": [
        "career-money"
      ]
    },
    {
      "id": "career-money-09-necktie-draped-empty-office-chair",
      "theme": "Career & Money",
      "category": "Career & Money",
      "url": "/boardimagelibrary/career-money/09-necktie-draped-empty-office-chair.png",
      "description": "Necktie draped empty office chair",
      "tags": [
        "career-money"
      ]
    },
    {
      "id": "career-money-10-hourglass-desk-bokeh-office-lights",
      "theme": "Career & Money",
      "category": "Career & Money",
      "url": "/boardimagelibrary/career-money/10-hourglass-desk-bokeh-office-lights.png",
      "description": "Hourglass desk bokeh office lights",
      "tags": [
        "career-money"
      ]
    },
    {
      "id": "career-money-11-wallet-credit-cards-fanned",
      "theme": "Career & Money",
      "category": "Career & Money",
      "url": "/boardimagelibrary/career-money/11-wallet-credit-cards-fanned.png",
      "description": "Wallet credit cards fanned",
      "tags": [
        "career-money"
      ]
    },
    {
      "id": "career-money-12-warehouse-aisle-organized-shelves",
      "theme": "Career & Money",
      "category": "Career & Money",
      "url": "/boardimagelibrary/career-money/12-warehouse-aisle-organized-shelves.png",
      "description": "Warehouse aisle organized shelves",
      "tags": [
        "career-money"
      ]
    },
    {
      "id": "career-money-13-hourglass-sand-desk",
      "theme": "Career & Money",
      "category": "Career & Money",
      "url": "/boardimagelibrary/career-money/13-hourglass-sand-desk.png",
      "description": "Hourglass sand desk",
      "tags": [
        "career-money"
      ]
    },
    {
      "id": "career-money-14-stock-market-candlestick-chart-monitor",
      "theme": "Career & Money",
      "category": "Career & Money",
      "url": "/boardimagelibrary/career-money/14-stock-market-candlestick-chart-monitor.png",
      "description": "Stock market candlestick chart monitor",
      "tags": [
        "career-money"
      ]
    },
    {
      "id": "career-money-15-leather-wallet-keys",
      "theme": "Career & Money",
      "category": "Career & Money",
      "url": "/boardimagelibrary/career-money/15-leather-wallet-keys.png",
      "description": "Leather wallet keys",
      "tags": [
        "career-money"
      ]
    },
    {
      "id": "career-money-16-conference-room-long-table-empty-morning-light",
      "theme": "Career & Money",
      "category": "Career & Money",
      "url": "/boardimagelibrary/career-money/16-conference-room-long-table-empty-morning-light.png",
      "description": "Conference room long table empty morning light",
      "tags": [
        "career-money"
      ]
    },
    {
      "id": "career-money-17-rising-bar-graph-sculpture-bronze",
      "theme": "Career & Money",
      "category": "Career & Money",
      "url": "/boardimagelibrary/career-money/17-rising-bar-graph-sculpture-bronze.png",
      "description": "Rising bar graph sculpture bronze",
      "tags": [
        "career-money"
      ]
    },
    {
      "id": "career-money-18-warehouse-aisle",
      "theme": "Career & Money",
      "category": "Career & Money",
      "url": "/boardimagelibrary/career-money/18-warehouse-aisle.png",
      "description": "Warehouse aisle",
      "tags": [
        "career-money"
      ]
    },
    {
      "id": "career-money-19-espresso-leather-portfolio-flat-lay",
      "theme": "Career & Money",
      "category": "Career & Money",
      "url": "/boardimagelibrary/career-money/19-espresso-leather-portfolio-flat-lay.png",
      "description": "Espresso leather portfolio flat lay",
      "tags": [
        "career-money"
      ]
    },
    {
      "id": "career-money-20-corner-office-window-empty-chair-silhouette",
      "theme": "Career & Money",
      "category": "Career & Money",
      "url": "/boardimagelibrary/career-money/20-corner-office-window-empty-chair-silhouette.png",
      "description": "Corner office window empty chair silhouette",
      "tags": [
        "career-money"
      ]
    },
    {
      "id": "love-relationships-01-heart-stones-beach",
      "theme": "Love & Relationships",
      "category": "Love & Relationships",
      "url": "/boardimagelibrary/love-relationships/01-heart-stones-beach.png",
      "description": "Heart stones beach",
      "tags": [
        "love-relationships"
      ]
    },
    {
      "id": "love-relationships-02-two-coffee-mugs",
      "theme": "Love & Relationships",
      "category": "Love & Relationships",
      "url": "/boardimagelibrary/love-relationships/02-two-coffee-mugs.png",
      "description": "Two coffee mugs",
      "tags": [
        "love-relationships"
      ]
    },
    {
      "id": "love-relationships-03-roses-bouquet",
      "theme": "Love & Relationships",
      "category": "Love & Relationships",
      "url": "/boardimagelibrary/love-relationships/03-roses-bouquet.png",
      "description": "Roses bouquet",
      "tags": [
        "love-relationships"
      ]
    },
    {
      "id": "love-relationships-04-wedding-rings-silk",
      "theme": "Love & Relationships",
      "category": "Love & Relationships",
      "url": "/boardimagelibrary/love-relationships/04-wedding-rings-silk.png",
      "description": "Wedding rings silk",
      "tags": [
        "love-relationships"
      ]
    },
    {
      "id": "love-relationships-05-letter-wax-seal",
      "theme": "Love & Relationships",
      "category": "Love & Relationships",
      "url": "/boardimagelibrary/love-relationships/05-letter-wax-seal.png",
      "description": "Letter wax seal",
      "tags": [
        "love-relationships"
      ]
    },
    {
      "id": "love-relationships-06-adirondack-chairs-lake",
      "theme": "Love & Relationships",
      "category": "Love & Relationships",
      "url": "/boardimagelibrary/love-relationships/06-adirondack-chairs-lake.png",
      "description": "Adirondack chairs lake",
      "tags": [
        "love-relationships"
      ]
    },
    {
      "id": "love-relationships-07-heart-sand-beach",
      "theme": "Love & Relationships",
      "category": "Love & Relationships",
      "url": "/boardimagelibrary/love-relationships/07-heart-sand-beach.png",
      "description": "Heart sand beach",
      "tags": [
        "love-relationships"
      ]
    },
    {
      "id": "love-relationships-08-padlock-heart-engraving",
      "theme": "Love & Relationships",
      "category": "Love & Relationships",
      "url": "/boardimagelibrary/love-relationships/08-padlock-heart-engraving.png",
      "description": "Padlock heart engraving",
      "tags": [
        "love-relationships"
      ]
    },
    {
      "id": "love-relationships-09-chocolate-box-ribbon",
      "theme": "Love & Relationships",
      "category": "Love & Relationships",
      "url": "/boardimagelibrary/love-relationships/09-chocolate-box-ribbon.png",
      "description": "Chocolate box ribbon",
      "tags": [
        "love-relationships"
      ]
    },
    {
      "id": "love-relationships-10-umbrella-rain-cobblestone",
      "theme": "Love & Relationships",
      "category": "Love & Relationships",
      "url": "/boardimagelibrary/love-relationships/10-umbrella-rain-cobblestone.png",
      "description": "Umbrella rain cobblestone",
      "tags": [
        "love-relationships"
      ]
    },
    {
      "id": "love-relationships-11-picnic-basket-meadow",
      "theme": "Love & Relationships",
      "category": "Love & Relationships",
      "url": "/boardimagelibrary/love-relationships/11-picnic-basket-meadow.png",
      "description": "Picnic basket meadow",
      "tags": [
        "love-relationships"
      ]
    },
    {
      "id": "love-relationships-12-swans-lake-dawn",
      "theme": "Love & Relationships",
      "category": "Love & Relationships",
      "url": "/boardimagelibrary/love-relationships/12-swans-lake-dawn.png",
      "description": "Swans lake dawn",
      "tags": [
        "love-relationships"
      ]
    },
    {
      "id": "love-relationships-13-moon-reflection-lake",
      "theme": "Love & Relationships",
      "category": "Love & Relationships",
      "url": "/boardimagelibrary/love-relationships/13-moon-reflection-lake.png",
      "description": "Moon reflection lake",
      "tags": [
        "love-relationships"
      ]
    },
    {
      "id": "love-relationships-14-twin-candles-table",
      "theme": "Love & Relationships",
      "category": "Love & Relationships",
      "url": "/boardimagelibrary/love-relationships/14-twin-candles-table.png",
      "description": "Twin candles table",
      "tags": [
        "love-relationships"
      ]
    },
    {
      "id": "love-relationships-15-bridge-sunset-reflection",
      "theme": "Love & Relationships",
      "category": "Love & Relationships",
      "url": "/boardimagelibrary/love-relationships/15-bridge-sunset-reflection.png",
      "description": "Bridge sunset reflection",
      "tags": [
        "love-relationships"
      ]
    },
    {
      "id": "love-relationships-16-ceramic-heart-sculpture",
      "theme": "Love & Relationships",
      "category": "Love & Relationships",
      "url": "/boardimagelibrary/love-relationships/16-ceramic-heart-sculpture.png",
      "description": "Ceramic heart sculpture",
      "tags": [
        "love-relationships"
      ]
    },
    {
      "id": "love-relationships-17-two-chairs-beach-sunset",
      "theme": "Love & Relationships",
      "category": "Love & Relationships",
      "url": "/boardimagelibrary/love-relationships/17-two-chairs-beach-sunset.png",
      "description": "Two chairs beach sunset",
      "tags": [
        "love-relationships"
      ]
    },
    {
      "id": "love-relationships-18-interlaced-hands-sunset",
      "theme": "Love & Relationships",
      "category": "Love & Relationships",
      "url": "/boardimagelibrary/love-relationships/18-interlaced-hands-sunset.png",
      "description": "Interlaced hands sunset",
      "tags": [
        "love-relationships"
      ]
    },
    {
      "id": "love-relationships-19-sealed-love-letter",
      "theme": "Love & Relationships",
      "category": "Love & Relationships",
      "url": "/boardimagelibrary/love-relationships/19-sealed-love-letter.png",
      "description": "Sealed love letter",
      "tags": [
        "love-relationships"
      ]
    },
    {
      "id": "love-relationships-20-roses-vase-window",
      "theme": "Love & Relationships",
      "category": "Love & Relationships",
      "url": "/boardimagelibrary/love-relationships/20-roses-vase-window.png",
      "description": "Roses vase window",
      "tags": [
        "love-relationships"
      ]
    },
    {
      "id": "home-space-01-cozy-living-room-fireplace",
      "theme": "Home & Space",
      "category": "Home & Space",
      "url": "/boardimagelibrary/home-space/01-cozy-living-room-fireplace.png",
      "description": "Cozy living room fireplace",
      "tags": [
        "home-space"
      ]
    },
    {
      "id": "home-space-02-kitchen-herb-garden-windowsill",
      "theme": "Home & Space",
      "category": "Home & Space",
      "url": "/boardimagelibrary/home-space/02-kitchen-herb-garden-windowsill.png",
      "description": "Kitchen herb garden windowsill",
      "tags": [
        "home-space"
      ]
    },
    {
      "id": "home-space-03-made-bed-white-linens",
      "theme": "Home & Space",
      "category": "Home & Space",
      "url": "/boardimagelibrary/home-space/03-made-bed-white-linens.png",
      "description": "Made bed white linens",
      "tags": [
        "home-space"
      ]
    },
    {
      "id": "home-space-04-reading-nook-armchair",
      "theme": "Home & Space",
      "category": "Home & Space",
      "url": "/boardimagelibrary/home-space/04-reading-nook-armchair.png",
      "description": "Reading nook armchair",
      "tags": [
        "home-space"
      ]
    },
    {
      "id": "home-space-05-spa-bathroom-candles-towels",
      "theme": "Home & Space",
      "category": "Home & Space",
      "url": "/boardimagelibrary/home-space/05-spa-bathroom-candles-towels.png",
      "description": "Spa bathroom candles towels",
      "tags": [
        "home-space"
      ]
    },
    {
      "id": "home-space-06-front-door-seasonal-wreath",
      "theme": "Home & Space",
      "category": "Home & Space",
      "url": "/boardimagelibrary/home-space/06-front-door-seasonal-wreath.png",
      "description": "Front door seasonal wreath",
      "tags": [
        "home-space"
      ]
    },
    {
      "id": "home-space-07-patio-garden-furniture",
      "theme": "Home & Space",
      "category": "Home & Space",
      "url": "/boardimagelibrary/home-space/07-patio-garden-furniture.png",
      "description": "Patio garden furniture",
      "tags": [
        "home-space"
      ]
    },
    {
      "id": "home-space-08-folded-laundry-wooden-table",
      "theme": "Home & Space",
      "category": "Home & Space",
      "url": "/boardimagelibrary/home-space/08-folded-laundry-wooden-table.png",
      "description": "Folded laundry wooden table",
      "tags": [
        "home-space"
      ]
    },
    {
      "id": "home-space-09-organized-bookshelf-plants",
      "theme": "Home & Space",
      "category": "Home & Space",
      "url": "/boardimagelibrary/home-space/09-organized-bookshelf-plants.png",
      "description": "Organized bookshelf plants",
      "tags": [
        "home-space"
      ]
    },
    {
      "id": "home-space-10-dining-table-set-for-two",
      "theme": "Home & Space",
      "category": "Home & Space",
      "url": "/boardimagelibrary/home-space/10-dining-table-set-for-two.png",
      "description": "Dining table set for two",
      "tags": [
        "home-space"
      ]
    },
    {
      "id": "home-space-11-houseplants-bright-corner",
      "theme": "Home & Space",
      "category": "Home & Space",
      "url": "/boardimagelibrary/home-space/11-houseplants-bright-corner.png",
      "description": "Houseplants bright corner",
      "tags": [
        "home-space"
      ]
    },
    {
      "id": "home-space-12-scandinavian-minimalist-living-room",
      "theme": "Home & Space",
      "category": "Home & Space",
      "url": "/boardimagelibrary/home-space/12-scandinavian-minimalist-living-room.png",
      "description": "Scandinavian minimalist living room",
      "tags": [
        "home-space"
      ]
    },
    {
      "id": "home-space-13-keys-entryway-hook",
      "theme": "Home & Space",
      "category": "Home & Space",
      "url": "/boardimagelibrary/home-space/13-keys-entryway-hook.png",
      "description": "Keys entryway hook",
      "tags": [
        "home-space"
      ]
    },
    {
      "id": "home-space-14-throw-pillows-linen-sofa",
      "theme": "Home & Space",
      "category": "Home & Space",
      "url": "/boardimagelibrary/home-space/14-throw-pillows-linen-sofa.png",
      "description": "Throw pillows linen sofa",
      "tags": [
        "home-space"
      ]
    },
    {
      "id": "home-space-15-organized-garage-tool-wall",
      "theme": "Home & Space",
      "category": "Home & Space",
      "url": "/boardimagelibrary/home-space/15-organized-garage-tool-wall.png",
      "description": "Organized garage tool wall",
      "tags": [
        "home-space"
      ]
    },
    {
      "id": "home-space-16-nursery-mobile-crib",
      "theme": "Home & Space",
      "category": "Home & Space",
      "url": "/boardimagelibrary/home-space/16-nursery-mobile-crib.png",
      "description": "Nursery mobile crib",
      "tags": [
        "home-space"
      ]
    },
    {
      "id": "home-space-17-home-office-desk-lamp",
      "theme": "Home & Space",
      "category": "Home & Space",
      "url": "/boardimagelibrary/home-space/17-home-office-desk-lamp.png",
      "description": "Home office desk lamp",
      "tags": [
        "home-space"
      ]
    },
    {
      "id": "home-space-18-keys-hanging-entryway",
      "theme": "Home & Space",
      "category": "Home & Space",
      "url": "/boardimagelibrary/home-space/18-keys-hanging-entryway.png",
      "description": "Keys hanging entryway",
      "tags": [
        "home-space"
      ]
    },
    {
      "id": "home-space-19-smart-thermostat-wall",
      "theme": "Home & Space",
      "category": "Home & Space",
      "url": "/boardimagelibrary/home-space/19-smart-thermostat-wall.png",
      "description": "Smart thermostat wall",
      "tags": [
        "home-space"
      ]
    },
    {
      "id": "home-space-20-cozy-blanket-basket",
      "theme": "Home & Space",
      "category": "Home & Space",
      "url": "/boardimagelibrary/home-space/20-cozy-blanket-basket.png",
      "description": "Cozy blanket basket",
      "tags": [
        "home-space"
      ]
    },
    {
      "id": "beauty-wellness-01-beauty-wellness-01-spa-stones",
      "theme": "Beauty & Wellness",
      "category": "Beauty & Wellness",
      "url": "/boardimagelibrary/beauty-wellness/01-beauty-wellness-01-spa-stones.png",
      "description": "Beauty wellness 01 spa stones",
      "tags": [
        "beauty-wellness"
      ]
    },
    {
      "id": "beauty-wellness-02-beauty-wellness-01",
      "theme": "Beauty & Wellness",
      "category": "Beauty & Wellness",
      "url": "/boardimagelibrary/beauty-wellness/02-beauty-wellness-01.png",
      "description": "Beauty wellness 01",
      "tags": [
        "beauty-wellness"
      ]
    },
    {
      "id": "beauty-wellness-03-beauty-wellness-02-yoga-mat",
      "theme": "Beauty & Wellness",
      "category": "Beauty & Wellness",
      "url": "/boardimagelibrary/beauty-wellness/03-beauty-wellness-02-yoga-mat.png",
      "description": "Beauty wellness 02 yoga mat",
      "tags": [
        "beauty-wellness"
      ]
    },
    {
      "id": "beauty-wellness-04-beauty-wellness-02",
      "theme": "Beauty & Wellness",
      "category": "Beauty & Wellness",
      "url": "/boardimagelibrary/beauty-wellness/04-beauty-wellness-02.png",
      "description": "Beauty wellness 02",
      "tags": [
        "beauty-wellness"
      ]
    },
    {
      "id": "beauty-wellness-05-beauty-wellness-03-essential-oils",
      "theme": "Beauty & Wellness",
      "category": "Beauty & Wellness",
      "url": "/boardimagelibrary/beauty-wellness/05-beauty-wellness-03-essential-oils.png",
      "description": "Beauty wellness 03 essential oils",
      "tags": [
        "beauty-wellness"
      ]
    },
    {
      "id": "beauty-wellness-06-beauty-wellness-03",
      "theme": "Beauty & Wellness",
      "category": "Beauty & Wellness",
      "url": "/boardimagelibrary/beauty-wellness/06-beauty-wellness-03.png",
      "description": "Beauty wellness 03",
      "tags": [
        "beauty-wellness"
      ]
    },
    {
      "id": "beauty-wellness-07-beauty-wellness-04",
      "theme": "Beauty & Wellness",
      "category": "Beauty & Wellness",
      "url": "/boardimagelibrary/beauty-wellness/07-beauty-wellness-04.png",
      "description": "Beauty wellness 04",
      "tags": [
        "beauty-wellness"
      ]
    },
    {
      "id": "beauty-wellness-08-beauty-wellness-05",
      "theme": "Beauty & Wellness",
      "category": "Beauty & Wellness",
      "url": "/boardimagelibrary/beauty-wellness/08-beauty-wellness-05.png",
      "description": "Beauty wellness 05",
      "tags": [
        "beauty-wellness"
      ]
    },
    {
      "id": "beauty-wellness-09-beauty-wellness-06",
      "theme": "Beauty & Wellness",
      "category": "Beauty & Wellness",
      "url": "/boardimagelibrary/beauty-wellness/09-beauty-wellness-06.png",
      "description": "Beauty wellness 06",
      "tags": [
        "beauty-wellness"
      ]
    },
    {
      "id": "beauty-wellness-10-beauty-wellness-07",
      "theme": "Beauty & Wellness",
      "category": "Beauty & Wellness",
      "url": "/boardimagelibrary/beauty-wellness/10-beauty-wellness-07.png",
      "description": "Beauty wellness 07",
      "tags": [
        "beauty-wellness"
      ]
    },
    {
      "id": "beauty-wellness-11-beauty-wellness-08",
      "theme": "Beauty & Wellness",
      "category": "Beauty & Wellness",
      "url": "/boardimagelibrary/beauty-wellness/11-beauty-wellness-08.png",
      "description": "Beauty wellness 08",
      "tags": [
        "beauty-wellness"
      ]
    },
    {
      "id": "beauty-wellness-12-beauty-wellness-09",
      "theme": "Beauty & Wellness",
      "category": "Beauty & Wellness",
      "url": "/boardimagelibrary/beauty-wellness/12-beauty-wellness-09.png",
      "description": "Beauty wellness 09",
      "tags": [
        "beauty-wellness"
      ]
    },
    {
      "id": "beauty-wellness-13-beauty-wellness-10",
      "theme": "Beauty & Wellness",
      "category": "Beauty & Wellness",
      "url": "/boardimagelibrary/beauty-wellness/13-beauty-wellness-10.png",
      "description": "Beauty wellness 10",
      "tags": [
        "beauty-wellness"
      ]
    },
    {
      "id": "beauty-wellness-14-beauty-wellness-11",
      "theme": "Beauty & Wellness",
      "category": "Beauty & Wellness",
      "url": "/boardimagelibrary/beauty-wellness/14-beauty-wellness-11.png",
      "description": "Beauty wellness 11",
      "tags": [
        "beauty-wellness"
      ]
    },
    {
      "id": "beauty-wellness-15-beauty-wellness-12",
      "theme": "Beauty & Wellness",
      "category": "Beauty & Wellness",
      "url": "/boardimagelibrary/beauty-wellness/15-beauty-wellness-12.png",
      "description": "Beauty wellness 12",
      "tags": [
        "beauty-wellness"
      ]
    },
    {
      "id": "beauty-wellness-16-beauty-wellness-13",
      "theme": "Beauty & Wellness",
      "category": "Beauty & Wellness",
      "url": "/boardimagelibrary/beauty-wellness/16-beauty-wellness-13.png",
      "description": "Beauty wellness 13",
      "tags": [
        "beauty-wellness"
      ]
    },
    {
      "id": "beauty-wellness-17-beauty-wellness-14",
      "theme": "Beauty & Wellness",
      "category": "Beauty & Wellness",
      "url": "/boardimagelibrary/beauty-wellness/17-beauty-wellness-14.png",
      "description": "Beauty wellness 14",
      "tags": [
        "beauty-wellness"
      ]
    },
    {
      "id": "beauty-wellness-18-beauty-wellness-15",
      "theme": "Beauty & Wellness",
      "category": "Beauty & Wellness",
      "url": "/boardimagelibrary/beauty-wellness/18-beauty-wellness-15.png",
      "description": "Beauty wellness 15",
      "tags": [
        "beauty-wellness"
      ]
    },
    {
      "id": "beauty-wellness-19-beauty-wellness-16",
      "theme": "Beauty & Wellness",
      "category": "Beauty & Wellness",
      "url": "/boardimagelibrary/beauty-wellness/19-beauty-wellness-16.png",
      "description": "Beauty wellness 16",
      "tags": [
        "beauty-wellness"
      ]
    },
    {
      "id": "beauty-wellness-20-beauty-wellness-17",
      "theme": "Beauty & Wellness",
      "category": "Beauty & Wellness",
      "url": "/boardimagelibrary/beauty-wellness/20-beauty-wellness-17.png",
      "description": "Beauty wellness 17",
      "tags": [
        "beauty-wellness"
      ]
    },
    {
      "id": "travel-adventure-01-milky-way-starry-mountains",
      "theme": "Travel & Adventure",
      "category": "Travel & Adventure",
      "url": "/boardimagelibrary/travel-adventure/01-milky-way-starry-mountains.png",
      "description": "Milky way starry mountains",
      "tags": [
        "travel-adventure"
      ]
    },
    {
      "id": "travel-adventure-02-porch-swing-sunset",
      "theme": "Travel & Adventure",
      "category": "Travel & Adventure",
      "url": "/boardimagelibrary/travel-adventure/02-porch-swing-sunset.png",
      "description": "Porch swing sunset",
      "tags": [
        "travel-adventure"
      ]
    },
    {
      "id": "travel-adventure-03-suitcase-airport-floor",
      "theme": "Travel & Adventure",
      "category": "Travel & Adventure",
      "url": "/boardimagelibrary/travel-adventure/03-suitcase-airport-floor.png",
      "description": "Suitcase airport floor",
      "tags": [
        "travel-adventure"
      ]
    },
    {
      "id": "travel-adventure-04-airplane-wing-clouds",
      "theme": "Travel & Adventure",
      "category": "Travel & Adventure",
      "url": "/boardimagelibrary/travel-adventure/04-airplane-wing-clouds.png",
      "description": "Airplane wing clouds",
      "tags": [
        "travel-adventure"
      ]
    },
    {
      "id": "travel-adventure-05-trail-sign-forest",
      "theme": "Travel & Adventure",
      "category": "Travel & Adventure",
      "url": "/boardimagelibrary/travel-adventure/05-trail-sign-forest.png",
      "description": "Trail sign forest",
      "tags": [
        "travel-adventure"
      ]
    },
    {
      "id": "travel-adventure-06-campfire-night-stars",
      "theme": "Travel & Adventure",
      "category": "Travel & Adventure",
      "url": "/boardimagelibrary/travel-adventure/06-campfire-night-stars.png",
      "description": "Campfire night stars",
      "tags": [
        "travel-adventure"
      ]
    },
    {
      "id": "travel-adventure-07-eiffel-tower-dawn",
      "theme": "Travel & Adventure",
      "category": "Travel & Adventure",
      "url": "/boardimagelibrary/travel-adventure/07-eiffel-tower-dawn.png",
      "description": "Eiffel tower dawn",
      "tags": [
        "travel-adventure"
      ]
    },
    {
      "id": "travel-adventure-08-passport-stamps-flat-lay",
      "theme": "Travel & Adventure",
      "category": "Travel & Adventure",
      "url": "/boardimagelibrary/travel-adventure/08-passport-stamps-flat-lay.png",
      "description": "Passport stamps flat lay",
      "tags": [
        "travel-adventure"
      ]
    },
    {
      "id": "travel-adventure-09-hiking-backpack-trail",
      "theme": "Travel & Adventure",
      "category": "Travel & Adventure",
      "url": "/boardimagelibrary/travel-adventure/09-hiking-backpack-trail.png",
      "description": "Hiking backpack trail",
      "tags": [
        "travel-adventure"
      ]
    },
    {
      "id": "travel-adventure-10-luggage-tag-suitcase",
      "theme": "Travel & Adventure",
      "category": "Travel & Adventure",
      "url": "/boardimagelibrary/travel-adventure/10-luggage-tag-suitcase.png",
      "description": "Luggage tag suitcase",
      "tags": [
        "travel-adventure"
      ]
    },
    {
      "id": "travel-adventure-11-snorkel-tropical-beach",
      "theme": "Travel & Adventure",
      "category": "Travel & Adventure",
      "url": "/boardimagelibrary/travel-adventure/11-snorkel-tropical-beach.png",
      "description": "Snorkel tropical beach",
      "tags": [
        "travel-adventure"
      ]
    },
    {
      "id": "travel-adventure-12-fjord-norway-cliffs",
      "theme": "Travel & Adventure",
      "category": "Travel & Adventure",
      "url": "/boardimagelibrary/travel-adventure/12-fjord-norway-cliffs.png",
      "description": "Fjord norway cliffs",
      "tags": [
        "travel-adventure"
      ]
    },
    {
      "id": "travel-adventure-13-hot-air-balloons-valley",
      "theme": "Travel & Adventure",
      "category": "Travel & Adventure",
      "url": "/boardimagelibrary/travel-adventure/13-hot-air-balloons-valley.png",
      "description": "Hot air balloons valley",
      "tags": [
        "travel-adventure"
      ]
    },
    {
      "id": "travel-adventure-14-train-tracks-mountains",
      "theme": "Travel & Adventure",
      "category": "Travel & Adventure",
      "url": "/boardimagelibrary/travel-adventure/14-train-tracks-mountains.png",
      "description": "Train tracks mountains",
      "tags": [
        "travel-adventure"
      ]
    },
    {
      "id": "travel-adventure-15-tropical-beach-palm",
      "theme": "Travel & Adventure",
      "category": "Travel & Adventure",
      "url": "/boardimagelibrary/travel-adventure/15-tropical-beach-palm.png",
      "description": "Tropical beach palm",
      "tags": [
        "travel-adventure"
      ]
    },
    {
      "id": "travel-adventure-16-castle-turret-hill",
      "theme": "Travel & Adventure",
      "category": "Travel & Adventure",
      "url": "/boardimagelibrary/travel-adventure/16-castle-turret-hill.png",
      "description": "Castle turret hill",
      "tags": [
        "travel-adventure"
      ]
    },
    {
      "id": "travel-adventure-17-car-dashboard-highway",
      "theme": "Travel & Adventure",
      "category": "Travel & Adventure",
      "url": "/boardimagelibrary/travel-adventure/17-car-dashboard-highway.png",
      "description": "Car dashboard highway",
      "tags": [
        "travel-adventure"
      ]
    },
    {
      "id": "travel-adventure-18-alpine-trail-meadow",
      "theme": "Travel & Adventure",
      "category": "Travel & Adventure",
      "url": "/boardimagelibrary/travel-adventure/18-alpine-trail-meadow.png",
      "description": "Alpine trail meadow",
      "tags": [
        "travel-adventure"
      ]
    },
    {
      "id": "travel-adventure-19-packed-suitcase-bed",
      "theme": "Travel & Adventure",
      "category": "Travel & Adventure",
      "url": "/boardimagelibrary/travel-adventure/19-packed-suitcase-bed.png",
      "description": "Packed suitcase bed",
      "tags": [
        "travel-adventure"
      ]
    },
    {
      "id": "travel-adventure-20-desert-highway-vanishing",
      "theme": "Travel & Adventure",
      "category": "Travel & Adventure",
      "url": "/boardimagelibrary/travel-adventure/20-desert-highway-vanishing.png",
      "description": "Desert highway vanishing",
      "tags": [
        "travel-adventure"
      ]
    },
    {
      "id": "organization-plan-01-bullet-journal",
      "theme": "Organization & Plan",
      "category": "Organization & Plan",
      "url": "/boardimagelibrary/organization-plan/01-bullet-journal.png",
      "description": "Bullet journal",
      "tags": [
        "organization-plan"
      ]
    },
    {
      "id": "organization-plan-02-wall-calendar",
      "theme": "Organization & Plan",
      "category": "Organization & Plan",
      "url": "/boardimagelibrary/organization-plan/02-wall-calendar.png",
      "description": "Wall calendar",
      "tags": [
        "organization-plan"
      ]
    },
    {
      "id": "organization-plan-03-file-folders",
      "theme": "Organization & Plan",
      "category": "Organization & Plan",
      "url": "/boardimagelibrary/organization-plan/03-file-folders.png",
      "description": "File folders",
      "tags": [
        "organization-plan"
      ]
    },
    {
      "id": "organization-plan-04-kanban-board",
      "theme": "Organization & Plan",
      "category": "Organization & Plan",
      "url": "/boardimagelibrary/organization-plan/04-kanban-board.png",
      "description": "Kanban board",
      "tags": [
        "organization-plan"
      ]
    },
    {
      "id": "organization-plan-05-leather-planner",
      "theme": "Organization & Plan",
      "category": "Organization & Plan",
      "url": "/boardimagelibrary/organization-plan/05-leather-planner.png",
      "description": "Leather planner",
      "tags": [
        "organization-plan"
      ]
    },
    {
      "id": "organization-plan-06-analog-clock",
      "theme": "Organization & Plan",
      "category": "Organization & Plan",
      "url": "/boardimagelibrary/organization-plan/06-analog-clock.png",
      "description": "Analog clock",
      "tags": [
        "organization-plan"
      ]
    },
    {
      "id": "organization-plan-07-label-maker",
      "theme": "Organization & Plan",
      "category": "Organization & Plan",
      "url": "/boardimagelibrary/organization-plan/07-label-maker.png",
      "description": "Label maker",
      "tags": [
        "organization-plan"
      ]
    },
    {
      "id": "organization-plan-08-filing-cabinet",
      "theme": "Organization & Plan",
      "category": "Organization & Plan",
      "url": "/boardimagelibrary/organization-plan/08-filing-cabinet.png",
      "description": "Filing cabinet",
      "tags": [
        "organization-plan"
      ]
    },
    {
      "id": "organization-plan-09-label-maker-desk",
      "theme": "Organization & Plan",
      "category": "Organization & Plan",
      "url": "/boardimagelibrary/organization-plan/09-label-maker-desk.png",
      "description": "Label maker desk",
      "tags": [
        "organization-plan"
      ]
    },
    {
      "id": "organization-plan-10-clipboard-checklist",
      "theme": "Organization & Plan",
      "category": "Organization & Plan",
      "url": "/boardimagelibrary/organization-plan/10-clipboard-checklist.png",
      "description": "Clipboard checklist",
      "tags": [
        "organization-plan"
      ]
    },
    {
      "id": "organization-plan-11-filing-cabinet-drawers",
      "theme": "Organization & Plan",
      "category": "Organization & Plan",
      "url": "/boardimagelibrary/organization-plan/11-filing-cabinet-drawers.png",
      "description": "Filing cabinet drawers",
      "tags": [
        "organization-plan"
      ]
    },
    {
      "id": "organization-plan-12-timeline-whiteboard",
      "theme": "Organization & Plan",
      "category": "Organization & Plan",
      "url": "/boardimagelibrary/organization-plan/12-timeline-whiteboard.png",
      "description": "Timeline whiteboard",
      "tags": [
        "organization-plan"
      ]
    },
    {
      "id": "organization-plan-13-pomodoro-timer",
      "theme": "Organization & Plan",
      "category": "Organization & Plan",
      "url": "/boardimagelibrary/organization-plan/13-pomodoro-timer.png",
      "description": "Pomodoro timer",
      "tags": [
        "organization-plan"
      ]
    },
    {
      "id": "organization-plan-14-desk-organizer",
      "theme": "Organization & Plan",
      "category": "Organization & Plan",
      "url": "/boardimagelibrary/organization-plan/14-desk-organizer.png",
      "description": "Desk organizer",
      "tags": [
        "organization-plan"
      ]
    },
    {
      "id": "organization-plan-15-pomodoro-timer-desk",
      "theme": "Organization & Plan",
      "category": "Organization & Plan",
      "url": "/boardimagelibrary/organization-plan/15-pomodoro-timer-desk.png",
      "description": "Pomodoro timer desk",
      "tags": [
        "organization-plan"
      ]
    },
    {
      "id": "organization-plan-16-desk-organizer-pens",
      "theme": "Organization & Plan",
      "category": "Organization & Plan",
      "url": "/boardimagelibrary/organization-plan/16-desk-organizer-pens.png",
      "description": "Desk organizer pens",
      "tags": [
        "organization-plan"
      ]
    },
    {
      "id": "organization-plan-17-meal-prep",
      "theme": "Organization & Plan",
      "category": "Organization & Plan",
      "url": "/boardimagelibrary/organization-plan/17-meal-prep.png",
      "description": "Meal prep",
      "tags": [
        "organization-plan"
      ]
    },
    {
      "id": "organization-plan-18-goal-worksheet",
      "theme": "Organization & Plan",
      "category": "Organization & Plan",
      "url": "/boardimagelibrary/organization-plan/18-goal-worksheet.png",
      "description": "Goal worksheet",
      "tags": [
        "organization-plan"
      ]
    },
    {
      "id": "organization-plan-19-meal-prep-containers",
      "theme": "Organization & Plan",
      "category": "Organization & Plan",
      "url": "/boardimagelibrary/organization-plan/19-meal-prep-containers.png",
      "description": "Meal prep containers",
      "tags": [
        "organization-plan"
      ]
    },
    {
      "id": "organization-plan-20-goal-worksheet-pencil",
      "theme": "Organization & Plan",
      "category": "Organization & Plan",
      "url": "/boardimagelibrary/organization-plan/20-goal-worksheet-pencil.png",
      "description": "Goal worksheet pencil",
      "tags": [
        "organization-plan"
      ]
    },
    {
      "id": "aesthetic-mood-01-soft-pink-orange-gradient-clouds",
      "theme": "Aesthetic & Mood",
      "category": "Aesthetic & Mood",
      "url": "/boardimagelibrary/aesthetic-mood/01-soft-pink-orange-gradient-clouds.png",
      "description": "Soft pink orange gradient clouds",
      "tags": [
        "aesthetic-mood"
      ]
    },
    {
      "id": "aesthetic-mood-02-rain-droplets-window-bokeh",
      "theme": "Aesthetic & Mood",
      "category": "Aesthetic & Mood",
      "url": "/boardimagelibrary/aesthetic-mood/02-rain-droplets-window-bokeh.png",
      "description": "Rain droplets window bokeh",
      "tags": [
        "aesthetic-mood"
      ]
    },
    {
      "id": "aesthetic-mood-03-golden-wheat-field-sunset",
      "theme": "Aesthetic & Mood",
      "category": "Aesthetic & Mood",
      "url": "/boardimagelibrary/aesthetic-mood/03-golden-wheat-field-sunset.png",
      "description": "Golden wheat field sunset",
      "tags": [
        "aesthetic-mood"
      ]
    },
    {
      "id": "aesthetic-mood-04-minimal-white-architecture-shadows",
      "theme": "Aesthetic & Mood",
      "category": "Aesthetic & Mood",
      "url": "/boardimagelibrary/aesthetic-mood/04-minimal-white-architecture-shadows.png",
      "description": "Minimal white architecture shadows",
      "tags": [
        "aesthetic-mood"
      ]
    },
    {
      "id": "aesthetic-mood-05-neon-city-lights-bokeh",
      "theme": "Aesthetic & Mood",
      "category": "Aesthetic & Mood",
      "url": "/boardimagelibrary/aesthetic-mood/05-neon-city-lights-bokeh.png",
      "description": "Neon city lights bokeh",
      "tags": [
        "aesthetic-mood"
      ]
    },
    {
      "id": "aesthetic-mood-06-hygge-candles-knit-texture",
      "theme": "Aesthetic & Mood",
      "category": "Aesthetic & Mood",
      "url": "/boardimagelibrary/aesthetic-mood/06-hygge-candles-knit-texture.png",
      "description": "Hygge candles knit texture",
      "tags": [
        "aesthetic-mood"
      ]
    },
    {
      "id": "aesthetic-mood-07-film-grain-ocean-waves-teal",
      "theme": "Aesthetic & Mood",
      "category": "Aesthetic & Mood",
      "url": "/boardimagelibrary/aesthetic-mood/07-film-grain-ocean-waves-teal.png",
      "description": "Film grain ocean waves teal",
      "tags": [
        "aesthetic-mood"
      ]
    },
    {
      "id": "aesthetic-mood-08-pastel-cherry-blossom-soft-focus",
      "theme": "Aesthetic & Mood",
      "category": "Aesthetic & Mood",
      "url": "/boardimagelibrary/aesthetic-mood/08-pastel-cherry-blossom-soft-focus.png",
      "description": "Pastel cherry blossom soft focus",
      "tags": [
        "aesthetic-mood"
      ]
    },
    {
      "id": "aesthetic-mood-09-dark-academia-books-coffee-steam",
      "theme": "Aesthetic & Mood",
      "category": "Aesthetic & Mood",
      "url": "/boardimagelibrary/aesthetic-mood/09-dark-academia-books-coffee-steam.png",
      "description": "Dark academia books coffee steam",
      "tags": [
        "aesthetic-mood"
      ]
    },
    {
      "id": "aesthetic-mood-10-cottagecore-wicker-basket-wildflowers",
      "theme": "Aesthetic & Mood",
      "category": "Aesthetic & Mood",
      "url": "/boardimagelibrary/aesthetic-mood/10-cottagecore-wicker-basket-wildflowers.png",
      "description": "Cottagecore wicker basket wildflowers",
      "tags": [
        "aesthetic-mood"
      ]
    },
    {
      "id": "aesthetic-mood-11-vaporwave-sunset-grid-landscape",
      "theme": "Aesthetic & Mood",
      "category": "Aesthetic & Mood",
      "url": "/boardimagelibrary/aesthetic-mood/11-vaporwave-sunset-grid-landscape.png",
      "description": "Vaporwave sunset grid landscape",
      "tags": [
        "aesthetic-mood"
      ]
    },
    {
      "id": "aesthetic-mood-12-foggy-forest-morning-light-rays",
      "theme": "Aesthetic & Mood",
      "category": "Aesthetic & Mood",
      "url": "/boardimagelibrary/aesthetic-mood/12-foggy-forest-morning-light-rays.png",
      "description": "Foggy forest morning light rays",
      "tags": [
        "aesthetic-mood"
      ]
    },
    {
      "id": "aesthetic-mood-13-white-marble-gold-veining",
      "theme": "Aesthetic & Mood",
      "category": "Aesthetic & Mood",
      "url": "/boardimagelibrary/aesthetic-mood/13-white-marble-gold-veining.png",
      "description": "White marble gold veining",
      "tags": [
        "aesthetic-mood"
      ]
    },
    {
      "id": "aesthetic-mood-14-sage-green-linen-fabric-folds",
      "theme": "Aesthetic & Mood",
      "category": "Aesthetic & Mood",
      "url": "/boardimagelibrary/aesthetic-mood/14-sage-green-linen-fabric-folds.png",
      "description": "Sage green linen fabric folds",
      "tags": [
        "aesthetic-mood"
      ]
    },
    {
      "id": "aesthetic-mood-15-autumn-maple-leaves-flat-lay",
      "theme": "Aesthetic & Mood",
      "category": "Aesthetic & Mood",
      "url": "/boardimagelibrary/aesthetic-mood/15-autumn-maple-leaves-flat-lay.png",
      "description": "Autumn maple leaves flat lay",
      "tags": [
        "aesthetic-mood"
      ]
    },
    {
      "id": "aesthetic-mood-16-zen-stacked-stones-stream",
      "theme": "Aesthetic & Mood",
      "category": "Aesthetic & Mood",
      "url": "/boardimagelibrary/aesthetic-mood/16-zen-stacked-stones-stream.png",
      "description": "Zen stacked stones stream",
      "tags": [
        "aesthetic-mood"
      ]
    },
    {
      "id": "aesthetic-mood-17-vinyl-record-headphones-retro-desk",
      "theme": "Aesthetic & Mood",
      "category": "Aesthetic & Mood",
      "url": "/boardimagelibrary/aesthetic-mood/17-vinyl-record-headphones-retro-desk.png",
      "description": "Vinyl record headphones retro desk",
      "tags": [
        "aesthetic-mood"
      ]
    },
    {
      "id": "aesthetic-mood-18-warm-fairy-light-bokeh-dark",
      "theme": "Aesthetic & Mood",
      "category": "Aesthetic & Mood",
      "url": "/boardimagelibrary/aesthetic-mood/18-warm-fairy-light-bokeh-dark.png",
      "description": "Warm fairy light bokeh dark",
      "tags": [
        "aesthetic-mood"
      ]
    },
    {
      "id": "aesthetic-mood-19-minimal-desert-sand-ripples-beige",
      "theme": "Aesthetic & Mood",
      "category": "Aesthetic & Mood",
      "url": "/boardimagelibrary/aesthetic-mood/19-minimal-desert-sand-ripples-beige.png",
      "description": "Minimal desert sand ripples beige",
      "tags": [
        "aesthetic-mood"
      ]
    },
    {
      "id": "aesthetic-mood-20-starry-milky-way-mountains",
      "theme": "Aesthetic & Mood",
      "category": "Aesthetic & Mood",
      "url": "/boardimagelibrary/aesthetic-mood/20-starry-milky-way-mountains.png",
      "description": "Starry milky way mountains",
      "tags": [
        "aesthetic-mood"
      ]
    }
  ]
}